readonlyonce_property.py
readonlyonce_property-1.0.4.dist-info/DESCRIPTION.rst
readonlyonce_property-1.0.4.dist-info/METADATA
readonlyonce_property-1.0.4.dist-info/RECORD
readonlyonce_property-1.0.4.dist-info/WHEEL
readonlyonce_property-1.0.4.dist-info/metadata.json
readonlyonce_property-1.0.4.dist-info/top_level.txt
