Metadata-Version: 2.0
Name: readonlyonce-property
Version: 1.0.4
Summary: @readonlyonce_property decorator that cache its return value.
Home-page: https://github.com/dhilst/readonlyonce_property
Author: Daniel Hilst Selli <danielhilst@gmail.com>
Author-email: UNKNOWN
License: Apache 2.0
Platform: UNKNOWN
